[
    {
        "command": "INITIALIZE",
        "args": [2, 1024, 1000000, "https://some-url.com/load-data"],
        "expected_response": "Initialized cache"
    },
    {
        "command": "TRAIN",
        "args": [],
        "expected_response": "Trained cache"
    },
    {
        "command": "LOAD",
        "args": [1, 1],
        "expected_response": "Loaded cell"
    },
    {
        "command": "SEARCH",
        "args": {
            "n": 1,
            "k": 1,
            "xq": [1, 1]
        },
        "expected_response": ""
    }
]
